MANIFEST.in
README.rst
setup.cfg
setup.py
reprotest/__init__.py
reprotest/__main__.py
reprotest/build.py
reprotest/environ.py
reprotest/mdiffconf.py
reprotest/presets.py
reprotest/shell_syn.py
reprotest/utils.py
reprotest.egg-info/PKG-INFO
reprotest.egg-info/SOURCES.txt
reprotest.egg-info/dependency_links.txt
reprotest.egg-info/entry_points.txt
reprotest.egg-info/not-zip-safe
reprotest.egg-info/requires.txt
reprotest.egg-info/top_level.txt
reprotest/lib/VirtSubproc.py
reprotest/lib/__init__.py
reprotest/lib/adt_testbed.py
reprotest/lib/adtlog.py
reprotest/lib/system_interface/__init__.py
reprotest/lib/system_interface/arch.py
reprotest/lib/system_interface/debian.py
reprotest/lib/system_interface/fedora.py
reprotest/lib/system_interface/guix.py
reprotest/virt/autopkgtest-virt-chroot
reprotest/virt/autopkgtest-virt-lxc
reprotest/virt/autopkgtest-virt-lxd
reprotest/virt/autopkgtest-virt-null
reprotest/virt/autopkgtest-virt-qemu
reprotest/virt/autopkgtest-virt-schroot
reprotest/virt/autopkgtest-virt-ssh
tests/test_mdiffconf.py
tests/test_reprotest.py
tests/test_shell.py