Metadata-Version: 2.4
Name: reprotest
Version: 0.7.30
Summary: Build packages and check them for reproducibility.
Home-page: https://salsa.debian.org/reproducible-builds/reprotest
Author: Ximin Luo, Ceridwen
Author-email: infinity0@debian.org, ceridwenv@gmail.com
License: GPL-3+
Classifier: Development Status :: 3 - Alpha
Classifier: Intended Audience :: Developers
Classifier: License :: OSI Approved :: GNU General Public License v3 or later (GPLv3+)
Classifier: Operating System :: POSIX
Classifier: Programming Language :: Python
Classifier: Programming Language :: Python :: 3
Classifier: Programming Language :: Python :: 3.9
Classifier: Topic :: Utilities
Requires-Dist: rstr
Requires-Dist: distro
Provides-Extra: compare
Requires-Dist: diffoscope>=112; extra == "compare"
Dynamic: author
Dynamic: author-email
Dynamic: classifier
Dynamic: description
Dynamic: home-page
Dynamic: license
Dynamic: provides-extra
Dynamic: requires-dist
Dynamic: summary
